LICENSE
README.md
setup.py
milvus_ingestion/__init__.py
milvus_ingestion/buffer.py
milvus_ingestion/constants.py
milvus_ingestion/data_buffer.py
milvus_ingestion/data_info.py
milvus_ingestion/exceptions.py
milvus_ingestion/milvus_connector.py
milvus_ingestion/uploader.py
milvus_ingestion/util.py
milvus_ingestion.egg-info/PKG-INFO
milvus_ingestion.egg-info/SOURCES.txt
milvus_ingestion.egg-info/dependency_links.txt
milvus_ingestion.egg-info/requires.txt
milvus_ingestion.egg-info/top_level.txt