Metadata-Version: 2.1
Name: milvus-ingestion
Version: 0.5.0
Summary: A tool to help data ingestion for Milvus
Home-page: https://github.com/yhmo/milvus-ingestion
Author: yihua.mo
Author-email: yihua.mo@zilliz.com
License: Apache-2.0
Classifier: Programming Language :: Python :: 3.7
Classifier: Programming Language :: Python :: 3.8
Classifier: Programming Language :: Python :: 3.9
Classifier: Programming Language :: Python :: 3.10
Classifier: Programming Language :: Python :: 3.11
Requires-Python: >=3.7
License-File: LICENSE
